bvmlib/__init__.py
bvmlib/bvm.py
bvmlib-1.1.0.dist-info/LICENSE.md
bvmlib-1.1.0.dist-info/METADATA
bvmlib-1.1.0.dist-info/WHEEL
bvmlib-1.1.0.dist-info/top_level.txt
bvmlib-1.1.0.dist-info/RECORD
