Metadata-Version: 2.1
Name: bvmlib
Version: 1.1.0
Summary: Bayes Vulnerability for Microdata library
Home-page: https://github.com/nunesgh/bvm-library
Author: Gabriel Henrique Lopes Gomes Alves Nunes
Author-email: contact@nunesgh.com
Project-URL: Bug Tracker, https://github.com/nunesgh/bvm-library/issues
Project-URL: Documentation, https://nunesgh.github.io/bvm-library/
Project-URL: Source Code, https://github.com/nunesgh/bvm-library
Requires-Python: >=3.10.6
License-File: LICENSE.md
Requires-Dist: numpy >=1.24.2
Requires-Dist: pandas >=1.5.3
